cqlib_adapter/VERSION.txt
cqlib_adapter/__init__.py
cqlib_adapter/_version.py
cqlib_adapter/pennylane_ext/__init__.py
cqlib_adapter/pennylane_ext/cqlib_config.toml
cqlib_adapter/pennylane_ext/device.py
cqlib_adapter/qiskit_ext/__init__.py
cqlib_adapter/qiskit_ext/adapter.py
cqlib_adapter/qiskit_ext/api_client.py
cqlib_adapter/qiskit_ext/gates.py
cqlib_adapter/qiskit_ext/job.py
cqlib_adapter/qiskit_ext/sampler.py
cqlib_adapter/qiskit_ext/tianyan_backend.py
cqlib_adapter/qiskit_ext/tianyan_provider.py
cqlib_adapter-0.3.0.dist-info/licenses/LICENSE
cqlib_adapter-0.3.0.dist-info/METADATA
cqlib_adapter-0.3.0.dist-info/WHEEL
cqlib_adapter-0.3.0.dist-info/entry_points.txt
cqlib_adapter-0.3.0.dist-info/top_level.txt
cqlib_adapter-0.3.0.dist-info/RECORD
